cso/__init__.py
cso/version.py
cso-0.0.1.dist-info/LICENSE
cso-0.0.1.dist-info/METADATA
cso-0.0.1.dist-info/WHEEL
cso-0.0.1.dist-info/top_level.txt
cso-0.0.1.dist-info/RECORD
